quantizeutils/__init__.py
quantizeutils/fx/__init__.py
quantizeutils/fx/backend_config/__init__.py
quantizeutils/fx/backend_config/ai_edge_backend.py
quantizeutils/fx/backend_config/openvino_backend.py
quantizeutils/fx/utils/__init__.py
quantizeutils/fx/utils/post_process.py
quantizeutils/fx/utils/pre_process.py
quantizeutils-0.1.1.dist-info/LICENSE
quantizeutils-0.1.1.dist-info/METADATA
quantizeutils-0.1.1.dist-info/WHEEL
quantizeutils-0.1.1.dist-info/RECORD
