Metadata-Version: 2.3
Name: quantizeutils
Version: 0.1.1
Summary: quantization utility modules to bridge torch fx and PT2E quantized models, as well as ONNX and others, inspired by methods in mmdeploy, without the outdated dependencies and some features not found in it.
License: GPL-3.0-or-later
Author: Elisa Aleman
Author-email: elisa.claire.aleman.carreon@gmail.com
Requires-Python: >=3.12
Classifier: License :: OSI Approved :: GNU General Public License v3 or later (GPLv3+)
Classifier: Programming Language :: Python :: 3
Classifier: Programming Language :: Python :: 3.12
Classifier: Programming Language :: Python :: 3.13
Requires-Dist: ai-edge-torch (==0.4.0)
Requires-Dist: onnx (>=1.18.0,<2.0.0)
Requires-Dist: onnxruntime-gpu (>=1.22.0,<2.0.0)
Requires-Dist: tensorflow (==2.19.1)
Requires-Dist: torch (==2.6.0)
Requires-Dist: torchvision (==0.21.0)
